{"stats":{"minecraft:dropped":{"minecraft:gravel":1,"minecraft:smooth_stone_slab":1,"minecraft:iron_ore":1,"minecraft:white_stained_glass":1},"minecraft:mined":{"minecraft:white_bed":9,"minecraft:light_gray_bed":2,"minecraft:blue_bed":3},"minecraft:picked_up":{"minecraft:smooth_stone_slab":1,"minecraft:item_frame":24,"minecraft:white_stained_glass":1,"minecraft:player_head":1,"minecraft:iron_ore":1,"minecraft:gravel":1,"minecraft:painting":2},"minecraft:custom":{"minecraft:inspect_dropper":1,"minecraft:fill_cauldron":6,"minecraft:open_shulker_box":4,"minecraft:leave_game":14,"minecraft:time_since_death":579235,"minecraft:climb_one_cm":544,"minecraft:sprint_one_cm":145821,"minecraft:walk_one_cm":1152100,"minecraft:drop":4,"minecraft:sneak_time":23315,"minecraft:walk_under_water_one_cm":4772,"minecraft:jump":1661,"minecraft:interact_with_blast_furnace":1,"minecraft:walk_on_water_one_cm":4671,"minecraft:interact_with_cartography_table":1,"minecraft:tune_noteblock":6,"minecraft:play_one_minute":579235,"minecraft:pot_flower":6,"minecraft:time_since_rest":579235,"minecraft:damage_dealt":48,"minecraft:fly_one_cm":10217551,"minecraft:crouch_one_cm":36743,"minecraft:interact_with_smoker":3},"minecraft:used":{"minecraft:oak_trapdoor":41,"minecraft:petrified_oak_slab":12,"minecraft:jungle_leaves":3,"minecraft:polished_granite_stairs":8,"minecraft:granite_stairs":13,"minecraft:red_concrete":178,"minecraft:dead_horn_coral_block":43,"minecraft:armor_stand":1,"minecraft:spruce_slab":82,"minecraft:bone_block":85,"minecraft:light_gray_carpet":41,"minecraft:oak_sign":12,"minecraft:black_carpet":3,"minecraft:spruce_planks":2184,"minecraft:stone":323,"minecraft:white_shulker_box":2,"minecraft:brown_shulker_box":9,"minecraft:red_nether_brick_stairs":41,"minecraft:quartz_stairs":45,"minecraft:stripped_birch_wood":26,"minecraft:grass":57,"minecraft:sandstone_wall":2,"minecraft:player_head":2,"minecraft:smooth_sandstone_stairs":22,"minecraft:oak_door":15,"minecraft:debug_stick":7,"minecraft:dirt":39,"minecraft:birch_pressure_plate":2,"minecraft:anvil":1,"minecraft:lily_of_the_valley":2,"minecraft:white_carpet":4,"minecraft:hopper":8,"minecraft:spruce_stairs":56,"minecraft:cobblestone_wall":12,"minecraft:stone_stairs":6,"minecraft:nether_brick_slab":1,"minecraft:shulker_box":7,"minecraft:jungle_trapdoor":8,"minecraft:granite":858,"minecraft:spruce_fence":9,"minecraft:nether_brick_stairs":38,"minecraft:birch_door":15,"minecraft:glass":95,"minecraft:stone_brick_slab":374,"minecraft:red_shulker_box":6,"minecraft:bricks":554,"minecraft:coal_ore":4,"minecraft:bookshelf":3,"minecraft:quartz_slab":1,"minecraft:iron_block":4,"minecraft:lantern":22,"minecraft:grass_block":98,"minecraft:blue_orchid":3,"minecraft:brick_stairs":33,"minecraft:polished_andesite_stairs":2,"minecraft:quartz_block":386,"minecraft:dark_oak_leaves":19,"minecraft:dark_oak_slab":4,"minecraft:smooth_quartz":2,"minecraft:diorite_wall":2,"minecraft:stone_bricks":200,"minecraft:item_frame":65,"minecraft:light_gray_wool":83,"minecraft:tripwire_hook":18,"minecraft:birch_trapdoor":21,"minecraft:red_nether_brick_wall":2,"minecraft:black_stained_glass":25,"minecraft:tall_grass":15,"minecraft:emerald_block":35,"minecraft:scaffolding":37,"minecraft:blue_shulker_box":3,"minecraft:furnace":13,"minecraft:white_stained_glass_pane":9,"minecraft:podzol":10,"minecraft:polished_diorite_stairs":2,"minecraft:granite_wall":38,"minecraft:dead_bubble_coral_block":3,"minecraft:dead_brain_coral_fan":19,"minecraft:light_gray_bed":4,"minecraft:stripped_spruce_wood":16,"minecraft:dark_oak_stairs":12,"minecraft:water_bucket":26,"minecraft:light_blue_shulker_box":13,"minecraft:nether_brick_wall":25,"minecraft:cobblestone_stairs":145,"minecraft:sandstone_stairs":37,"minecraft:spruce_door":1,"minecraft:acacia_trapdoor":32,"minecraft:polished_andesite":270,"minecraft:cartography_table":9,"minecraft:polished_diorite_slab":4,"minecraft:sandstone":301,"minecraft:black_shulker_box":1,"minecraft:cut_sandstone":16,"minecraft:black_glazed_terracotta":241,"minecraft:cauldron":13,"minecraft:spruce_fence_gate":2,"minecraft:fletching_table":17,"minecraft:blue_bed":5,"minecraft:sugar_cane":4,"minecraft:cobblestone_slab":1897,"minecraft:oak_leaves":139,"minecraft:smooth_quartz_stairs":4,"minecraft:dark_oak_trapdoor":99,"minecraft:sand":3,"minecraft:light_gray_banner":2,"minecraft:cut_sandstone_slab":4,"minecraft:crafting_table":1,"minecraft:magenta_bed":2,"minecraft:dead_fire_coral_block":1,"minecraft:brown_banner":3,"minecraft:birch_sign":22,"minecraft:blast_furnace":12,"minecraft:light_gray_terracotta":83,"minecraft:campfire":4,"minecraft:white_bed":15,"minecraft:light_gray_concrete_powder":5,"minecraft:chiseled_quartz_block":2,"minecraft:note_block":13,"minecraft:gray_concrete":981,"minecraft:stone_brick_wall":16,"minecraft:painting":51,"minecraft:smooth_red_sandstone_stairs":13,"minecraft:smoker":56,"minecraft:red_sandstone_wall":7,"minecraft:dark_oak_door":4,"minecraft:redstone_torch":8,"minecraft:oak_log":35,"minecraft:black_terracotta":15,"minecraft:piston":10,"minecraft:lever":1,"minecraft:green_concrete":277,"minecraft:flower_pot":9,"minecraft:black_wool":9,"minecraft:daylight_detector":1,"minecraft:chiseled_sandstone":130,"minecraft:acacia_door":5,"minecraft:oak_button":2,"minecraft:stone_button":7,"minecraft:cyan_carpet":3,"minecraft:white_glazed_terracotta":190,"minecraft:purpur_slab":5,"minecraft:polished_granite":171,"minecraft:spruce_trapdoor":1,"minecraft:iron_door":2,"minecraft:gravel":26,"minecraft:blue_carpet":24,"minecraft:coal_block":20,"minecraft:cobblestone":1228,"minecraft:white_banner":6,"minecraft:stripped_oak_wood":53,"minecraft:pink_shulker_box":21,"minecraft:lapis_block":34,"minecraft:white_stained_glass":20,"minecraft:andesite":84,"minecraft:ice":5,"minecraft:glass_pane":393,"minecraft:mossy_cobblestone_wall":14,"minecraft:smooth_stone_slab":42,"minecraft:sea_pickle":21,"minecraft:white_concrete":1813,"minecraft:tropical_fish_bucket":8,"minecraft:coarse_dirt":52,"minecraft:dandelion":2,"minecraft:gray_wool":73,"minecraft:smooth_stone":152}},"DataVersion":1976}